ig_data/InstaSearch.py
ig_data/__init__.py
ig_data-0.0.2.dist-info/LICENSE
ig_data-0.0.2.dist-info/METADATA
ig_data-0.0.2.dist-info/WHEEL
ig_data-0.0.2.dist-info/top_level.txt
ig_data-0.0.2.dist-info/RECORD
