Metadata-Version: 2.1
Name: ig-data
Version: 0.0.2
Summary: A small package to extract instagram data for the given username
Home-page: https://github.com/swapnanildutta/instagram-search
Author: Swapnanil Dutta
Author-email: swapnanildutta2000@gmail.com
License: UNKNOWN
Platform: UNKNOWN
Classifier: Programming Language :: Python :: 3
Classifier: License :: OSI Approved :: MIT License
Classifier: Operating System :: OS Independent
Requires-Python: >=3.6
Requires-Dist: beautifulsoup4
Requires-Dist: requests
